AUTHORS.rst
CONTRIBUTING.rst
HISTORY.rst
LICENSE
MANIFEST.in
README.rst
setup.cfg
setup.py
docs/Makefile
docs/authors.rst
docs/conf.py
docs/contributing.rst
docs/history.rst
docs/index.rst
docs/installation.rst
docs/make.bat
docs/readme.rst
docs/usage.rst
easyaspymutations/__init__.py
easyaspymutations/cli.py
easyaspymutations/easyaspymutations.py
easyaspymutations.egg-info/PKG-INFO
easyaspymutations.egg-info/SOURCES.txt
easyaspymutations.egg-info/dependency_links.txt
easyaspymutations.egg-info/entry_points.txt
easyaspymutations.egg-info/not-zip-safe
easyaspymutations.egg-info/requires.txt
easyaspymutations.egg-info/top_level.txt
tests/__init__.py
tests/test_easyaspymutations.py