Metadata-Version: 1.2
Name: easyaspymutations
Version: 0.0.3
Summary: Assorted utility functions for working with mutation files (vcfs/mafs/etc)
Home-page: https://github.com/selkmand/easyaspymutations
Author: Sam El-Kamand
Author-email: selkamand@ccia.org.au
License: MIT license
Keywords: easyaspymutations
Platform: UNKNOWN
Classifier: Development Status :: 2 - Pre-Alpha
Classifier: Intended Audience :: Developers
Classifier: License :: OSI Approved :: MIT License
Classifier: Natural Language :: English
Classifier: Programming Language :: Python :: 3
Classifier: Programming Language :: Python :: 3.6
Classifier: Programming Language :: Python :: 3.7
Classifier: Programming Language :: Python :: 3.8
Requires-Python: >=3.6
